MANIFEST.in
README.rst
setup.py
nepserate/__init__.py
nepserate/csymbol.py
nepserate/scraperate.py
nepserate.egg-info/PKG-INFO
nepserate.egg-info/SOURCES.txt
nepserate.egg-info/dependency_links.txt
nepserate.egg-info/not-zip-safe
nepserate.egg-info/requires.txt
nepserate.egg-info/top_level.txt