Metadata-Version: 1.0
Name: nepserate
Version: 0.1.0
Summary: Get the stock price of banks and Organization of Nepal.
Home-page: https://github.com/acsudeep/nepserate
Author: Sudeep Acharya
Author-email: sudeep611@gmail.com
License: MIT
Keywords: nepal,nepse,nepalstock,nepalsharemarket
Platform: any
